treefolder/__init__.py
treefolder/tree.py
treefolder-1.0.0.dist-info/LICENSE
treefolder-1.0.0.dist-info/METADATA
treefolder-1.0.0.dist-info/WHEEL
treefolder-1.0.0.dist-info/entry_points.txt
treefolder-1.0.0.dist-info/top_level.txt
treefolder-1.0.0.dist-info/RECORD
