Metadata-Version: 2.1
Name: treefolder
Version: 1.0.0
Summary: A simple Python program that generates an ASCII representation of a directory tree.
Home-page: https://github.com/Aperezortega/Treefolder
Author: Alberto Perez Ortega
Author-email: apo0106@gmail.com
Classifier: Programming Language :: Python :: 3
Classifier: License :: OSI Approved :: MIT License
Classifier: Operating System :: OS Independent
Requires-Python: >=3.6
License-File: LICENSE
